ahjo/__init__.py
ahjo/action.py
ahjo/context.py
ahjo/credential_handler.py
ahjo/interface_methods.py
ahjo/operation_manager.py
ahjo/version.py
ahjo/database_utilities/__init__.py
ahjo/database_utilities/conn_info.py
ahjo/database_utilities/pyodbc_utilities.py
ahjo/database_utilities/sqla_utilities.py
ahjo/database_utilities/sqlcmd.py
ahjo/logging/__init__.py
ahjo/logging/db_formatter.py
ahjo/logging/db_handler.py
ahjo/logging/db_logger.py
ahjo/logging/winEventLogger.py
ahjo/logging/win_event_logger.py
ahjo/operations/__init__.py
ahjo/operations/general/__init__.py
ahjo/operations/general/alembic.py
ahjo/operations/general/bulk_insert.py
ahjo/operations/general/db_info.py
ahjo/operations/general/db_tester.py
ahjo/operations/general/git_hook.py
ahjo/operations/general/git_version.py
ahjo/operations/general/initialization.py
ahjo/operations/general/multi_project_build.py
ahjo/operations/general/scan.py
ahjo/operations/general/sqlfiles.py
ahjo/operations/general/upgrade.py
ahjo/operations/general/visualization.py
ahjo/operations/tsql/__init__.py
ahjo/operations/tsql/create_db.py
ahjo/operations/tsql/create_db_login.py
ahjo/operations/tsql/create_db_permissions.py
ahjo/operations/tsql/create_db_structure.py
ahjo/operations/tsql/db_info.py
ahjo/operations/tsql/db_object_properties.py
ahjo/operations/tsql/set_statements.py
ahjo/operations/tsql/sqlfiles.py
ahjo/resources/logger.ini
ahjo/resources/logger_alembic.ini
ahjo/resources/logger_root.ini
ahjo/resources/logger_sqlalchemy.ini
ahjo/resources/logger_winLog.ini
ahjo/resources/winEventLogger.py
ahjo/resources/files/.gitignore
ahjo/resources/files/ahjo_actions.py
ahjo/resources/files/alembic.ini
ahjo/resources/files/alembic_dummy
ahjo/resources/files/config_development.json
ahjo/resources/files/config_development.jsonc
ahjo/resources/files/config_development.yaml
ahjo/resources/files/env.py
ahjo/resources/files/script.py.mako
ahjo/resources/files/git_hooks/pre-commit
ahjo-3.11.1.dist-info/licenses/LICENSE
ahjo-3.11.1.dist-info/METADATA
ahjo-3.11.1.dist-info/WHEEL
ahjo-3.11.1.dist-info/entry_points.txt
ahjo-3.11.1.dist-info/top_level.txt
ahjo-3.11.1.dist-info/RECORD
