Metadata-Version: 2.4
Name: ahjo
Version: 3.11.1
Summary: Database deployment framework
Home-page: https://github.com/ALMPartners/ahjo
Author: ALM Partners Oy
Author-email: servicedesk@almpartners.fi
Keywords: ahjo
Classifier: Intended Audience :: Developers
Classifier: License :: OSI Approved :: Apache Software License
Classifier: Topic :: Database
Classifier: Programming Language :: Python :: 3.12
Classifier: Programming Language :: Python :: 3.13
Requires-Python: >=3.12
License-File: LICENSE
Requires-Dist: alembic~=1.15.0
Requires-Dist: pyparsing~=3.2.0
Requires-Dist: sqlalchemy~=2.0.0
Requires-Dist: PyYAML~=6.0.0
Requires-Dist: lark~=1.2.0
Requires-Dist: networkx~=3.4.0
Provides-Extra: mssql
Requires-Dist: pyodbc~=5.2.0; extra == "mssql"
Provides-Extra: azure
Requires-Dist: azure-identity~=1.21.0; extra == "azure"
Provides-Extra: visualizations
Requires-Dist: plotly~=6.0.0; extra == "visualizations"
Provides-Extra: dev
Requires-Dist: black~=25.1.0; extra == "dev"
Requires-Dist: pre-commit~=4.2.0; extra == "dev"
Requires-Dist: pytest~=8.3.4; extra == "dev"
Requires-Dist: tox~=4.24.1; extra == "dev"
Dynamic: license-file
